pyviber/__init__.py
pyviber/bot.py
pyviber/bot_info.py
pyviber/error_codes.py
pyviber/event_type.py
pyviber/keyboard.py
pyviber/message_type.py
pyviber/message_type_handlers.py
pyviber/sender.py
pyviber/user_info.py
pyviber/events/__init__.py
pyviber/events/conversation_started_event.py
pyviber/events/delivered_event.py
pyviber/events/event.py
pyviber/events/failed_event.py
pyviber/events/message_event.py
pyviber/events/seen_event.py
pyviber/events/subscribed_event.py
pyviber/events/unsubscribed_event.py
pyviber/messages/__init__.py
pyviber/messages/contact_message.py
pyviber/messages/file_message.py
pyviber/messages/location_message.py
pyviber/messages/message.py
pyviber/messages/picture_message.py
pyviber/messages/rich_media_message.py
pyviber/messages/sticker_message.py
pyviber/messages/text_message.py
pyviber/messages/url_message.py
pyviber/messages/video_message.py
pyviber-0.2.dist-info/LICENSE
pyviber-0.2.dist-info/METADATA
pyviber-0.2.dist-info/WHEEL
pyviber-0.2.dist-info/top_level.txt
pyviber-0.2.dist-info/RECORD
