Metadata-Version: 2.1
Name: pyviber
Version: 0.2
Summary: Python package for developing Viber Bots
Requires: aiohttp
Requires: asyncio
License-File: LICENSE
